Metadata-Version: 2.1
Name: JvMcControll
Version: 0.0.12
Summary: Este script Python é projetado para ajudar streamers de Minecraft Bedrock a tornar suas transmissões mais interativas, permitindo que o chat envie comandos diretamente ao jogo por meio de uma conexão WebSocket.
Home-page: UNKNOWN
Author: Jvsm Games
Author-email: jvsm5000wt@gmail.com
License: MIT License
Keywords: websocket
Platform: UNKNOWN
License-File: LICENCE
